crank4py_connector/__init__.py
crank4py_connector/config.py
crank4py_connector/conn_info_n_ws_client_farm.py
crank4py_connector/connector.py
crank4py_connector/connector_socket.py
crank4py_connector/intermediate_request.py
crank4py_connector/version.py
cranker_protocol/__init__.py
cranker_protocol/protocol.py
test/__init__.py
test/test_connector_with_flask.py
util/__init__.py
crank4py_connector-0.0.5.dist-info/LICENSE
crank4py_connector-0.0.5.dist-info/METADATA
crank4py_connector-0.0.5.dist-info/WHEEL
crank4py_connector-0.0.5.dist-info/top_level.txt
crank4py_connector-0.0.5.dist-info/RECORD
