Metadata-Version: 2.1
Name: crank4py-connector
Version: 0.0.5
Summary: A python library that allows web services to be registered to one or more cranker routers(Api gateway)
Home-page: https://github.com/torchcc/crank4py-connector
Author: torchcc
Author-email: 1553765526@qq.com
License: UNKNOWN
Platform: UNKNOWN
Classifier: Programming Language :: Python :: 3
Classifier: License :: OSI Approved :: MIT License
Classifier: Operating System :: OS Independent
Requires-Python: >=3.6
License-File: LICENSE
Requires-Dist: websocket-client (==1.1.0)
Requires-Dist: requests
Requires-Dist: yarl
